<?xml version="1.0"?>
<resources>
  <hardware>
    <mpi_size>4</mpi_size>
    <mpi>true</mpi>
    <openmp_threads>1</openmp_threads>
    <openmp>true</openmp>
    <gpu>false</gpu>
  </hardware>
  <timing>
    <max_stack_level_exceeded>no</max_stack_level_exceeded>
    <max_timers_exceeded>no</max_timers_exceeded>
    <timer>
      <name>Total</name>
      <time_incl>63.0051</time_incl>
      <time_excl>0.00834921</time_excl>
      <calls>1</calls>
      <includes>
        <timer>
          <name>DMC</name>
          <time_incl>62.7733</time_incl>
          <time_excl>62.7733</time_excl>
          <calls>2</calls>
        </timer>
        <timer>
          <name>Startup</name>
          <time_incl>0.059567</time_incl>
          <time_excl>0.059567</time_excl>
          <calls>1</calls>
        </timer>
        <timer>
          <name>VMC</name>
          <time_incl>0.1639</time_incl>
          <time_excl>0.1639</time_excl>
          <calls>1</calls>
        </timer>
      </includes>
    </timer>
  </timing>
  <particles>
    <particle>
      <name>e</name>
      <size>2</size>
    </particle>
    <particle>
      <name>ion0</name>
      <size>2</size>
    </particle>
  </particles>
</resources>
